{
"meta":{"test_sets":[],"test_metrics":[],"learn_metrics":[{"best_value":"Min","name":"RMSE"}],"launch_mode":"Train","parameters":"","iteration_count":100,"learn_sets":["learn"],"name":"experiment"},
"iterations":[
{"learn":[14.005006],"iteration":0,"passed_time":0.005232371875,"remaining_time":0.5180048156},
{"learn":[13.14441192],"iteration":1,"passed_time":0.00956749831,"remaining_time":0.4688074172},
{"learn":[12.34258257],"iteration":2,"passed_time":0.01437508917,"remaining_time":0.4647945498},
{"learn":[11.64527793],"iteration":3,"passed_time":0.01714469372,"remaining_time":0.4114726494},
{"learn":[11.02766183],"iteration":4,"passed_time":0.01989653809,"remaining_time":0.3780342237},
{"learn":[10.43485794],"iteration":5,"passed_time":0.02240774144,"remaining_time":0.3510546158},
{"learn":[9.890641275],"iteration":6,"passed_time":0.02505469264,"remaining_time":0.3328694879},
{"learn":[9.492161212],"iteration":7,"passed_time":0.02757263125,"remaining_time":0.3170852593},
{"learn":[9.105082953],"iteration":8,"passed_time":0.02981631917,"remaining_time":0.3014761161},
{"learn":[8.674157135],"iteration":9,"passed_time":0.03158780984,"remaining_time":0.2842902886},
{"learn":[8.341743544],"iteration":10,"passed_time":0.0336187054,"remaining_time":0.2720058891},
{"learn":[8.049372916],"iteration":11,"passed_time":0.03620813357,"remaining_time":0.2655263129},
{"learn":[7.757318612],"iteration":12,"passed_time":0.03875319487,"remaining_time":0.2593483042},
{"learn":[7.522206899],"iteration":13,"passed_time":0.04113337494,"remaining_time":0.2526764461},
{"learn":[7.297756655],"iteration":14,"passed_time":0.04376891185,"remaining_time":0.2480238338},
{"learn":[7.088359431],"iteration":15,"passed_time":0.04636203648,"remaining_time":0.2434006915},
{"learn":[6.882113791],"iteration":16,"passed_time":0.04886254705,"remaining_time":0.2385642003},
{"learn":[6.704728832],"iteration":17,"passed_time":0.05136302374,"remaining_time":0.2339871082},
{"learn":[6.563881962],"iteration":18,"passed_time":0.05408857414,"remaining_time":0.2305881318},
{"learn":[6.418790279],"iteration":19,"passed_time":0.05661464828,"remaining_time":0.2264585931},
{"learn":[6.315756953],"iteration":20,"passed_time":0.05914849524,"remaining_time":0.2225110059},
{"learn":[6.210157751],"iteration":21,"passed_time":0.06156737614,"remaining_time":0.2182843336},
{"learn":[6.115058449],"iteration":22,"passed_time":0.06418681085,"remaining_time":0.2148862798},
{"learn":[6.014819884],"iteration":23,"passed_time":0.06669711494,"remaining_time":0.2112075306},
{"learn":[5.93117229],"iteration":24,"passed_time":0.069183033,"remaining_time":0.207549099},
{"learn":[5.844857622],"iteration":25,"passed_time":0.07178639438,"remaining_time":0.2043151225},
{"learn":[5.771145213],"iteration":26,"passed_time":0.07426896758,"remaining_time":0.2008012827},
{"learn":[5.704018229],"iteration":27,"passed_time":0.07741172223,"remaining_time":0.1990587143},
{"learn":[5.665806474],"iteration":28,"passed_time":0.08007171794,"remaining_time":0.1960376543},
{"learn":[5.616500369],"iteration":29,"passed_time":0.08240635471,"remaining_time":0.1922814943},
{"learn":[5.558023666],"iteration":30,"passed_time":0.08438850597,"remaining_time":0.187832481},
{"learn":[5.510080976],"iteration":31,"passed_time":0.08660926033,"remaining_time":0.1840446782},
{"learn":[5.468747792],"iteration":32,"passed_time":0.08880699449,"remaining_time":0.18030511},
{"learn":[5.429275534],"iteration":33,"passed_time":0.09147593945,"remaining_time":0.1775709413},
{"learn":[5.402117324],"iteration":34,"passed_time":0.09359694902,"remaining_time":0.1738229053},
{"learn":[5.367635151],"iteration":35,"passed_time":0.09538946476,"remaining_time":0.1695812707},
{"learn":[5.345181232],"iteration":36,"passed_time":0.09748531235,"remaining_time":0.1659885048},
{"learn":[5.319151269],"iteration":37,"passed_time":0.09884306415,"remaining_time":0.1612702626},
{"learn":[5.296134146],"iteration":38,"passed_time":0.1003541074,"remaining_time":0.1569641167},
{"learn":[5.269629003],"iteration":39,"passed_time":0.1026947696,"remaining_time":0.1540421543},
{"learn":[5.251147059],"iteration":40,"passed_time":0.1041461291,"remaining_time":0.1498688199},
{"learn":[5.248003302],"iteration":41,"passed_time":0.104672404,"remaining_time":0.1445476055},
{"learn":[5.232376509],"iteration":42,"passed_time":0.1059638468,"remaining_time":0.1404637039},
{"learn":[5.213524255],"iteration":43,"passed_time":0.1070661857,"remaining_time":0.1362660545},
{"learn":[5.189691584],"iteration":44,"passed_time":0.1081094274,"remaining_time":0.1321337446},
{"learn":[5.166052198],"iteration":45,"passed_time":0.1094508303,"remaining_time":0.1284857574},
{"learn":[5.140406659],"iteration":46,"passed_time":0.1107759545,"remaining_time":0.1249175657},
{"learn":[5.118929684],"iteration":47,"passed_time":0.1132470723,"remaining_time":0.1226843283},
{"learn":[5.108792602],"iteration":48,"passed_time":0.1151323854,"remaining_time":0.1198316664},
{"learn":[5.098141225],"iteration":49,"passed_time":0.1170143864,"remaining_time":0.1170143864},
{"learn":[5.085926393],"iteration":50,"passed_time":0.1192385028,"remaining_time":0.1145624831},
{"learn":[5.067816804],"iteration":51,"passed_time":0.1208210206,"remaining_time":0.1115270959},
{"learn":[5.049834901],"iteration":52,"passed_time":0.1224259154,"remaining_time":0.1085663778},
{"learn":[5.03838627],"iteration":53,"passed_time":0.1240165143,"remaining_time":0.1056436974},
{"learn":[5.033534248],"iteration":54,"passed_time":0.1249729752,"remaining_time":0.1022506161},
{"learn":[5.023726885],"iteration":55,"passed_time":0.1266580283,"remaining_time":0.09951702222},
{"learn":[5.01290392],"iteration":56,"passed_time":0.128247478,"remaining_time":0.09674809741},
{"learn":[5.005569127],"iteration":57,"passed_time":0.130223235,"remaining_time":0.09429958396},
{"learn":[4.989969032],"iteration":58,"passed_time":0.1325377532,"remaining_time":0.09210250644},
{"learn":[4.976762446],"iteration":59,"passed_time":0.1337868581,"remaining_time":0.08919123876},
{"learn":[4.967222715],"iteration":60,"passed_time":0.1355080048,"remaining_time":0.0866362654},
{"learn":[4.954407599],"iteration":61,"passed_time":0.136731233,"remaining_time":0.08380301377},
{"learn":[4.942125056],"iteration":62,"passed_time":0.1376824961,"remaining_time":0.08086114849},
{"learn":[4.930230716],"iteration":63,"passed_time":0.1388092848,"remaining_time":0.07808022272},
{"learn":[4.921695642],"iteration":64,"passed_time":0.1471769196,"remaining_time":0.07924911055},
{"learn":[4.906405625],"iteration":65,"passed_time":0.1526713564,"remaining_time":0.07864888055},
{"learn":[4.894330248],"iteration":66,"passed_time":0.1555523794,"remaining_time":0.07661535104},
{"learn":[4.88211557],"iteration":67,"passed_time":0.1583097448,"remaining_time":0.07449870345},
{"learn":[4.877946398],"iteration":68,"passed_time":0.1607903262,"remaining_time":0.07223913207},
{"learn":[4.863182126],"iteration":69,"passed_time":0.1630340069,"remaining_time":0.06987171725},
{"learn":[4.84646533],"iteration":70,"passed_time":0.1653942806,"remaining_time":0.06755541037},
{"learn":[4.838014752],"iteration":71,"passed_time":0.1674390177,"remaining_time":0.06511517355},
{"learn":[4.82981137],"iteration":72,"passed_time":0.1689921166,"remaining_time":0.06250393354},
{"learn":[4.817094767],"iteration":73,"passed_time":0.17049418,"remaining_time":0.05990336055},
{"learn":[4.808314151],"iteration":74,"passed_time":0.1720816329,"remaining_time":0.0573605443},
{"learn":[4.796235023],"iteration":75,"passed_time":0.1735791789,"remaining_time":0.05481447755},
{"learn":[4.784434534],"iteration":76,"passed_time":0.1752541408,"remaining_time":0.05234863946},
{"learn":[4.774402487],"iteration":77,"passed_time":0.1765650601,"remaining_time":0.04980040157},
{"learn":[4.76731896],"iteration":78,"passed_time":0.178248067,"remaining_time":0.04738239755},
{"learn":[4.75934113],"iteration":79,"passed_time":0.1802835005,"remaining_time":0.04507087512},
{"learn":[4.754106378],"iteration":80,"passed_time":0.1821506063,"remaining_time":0.04272668542},
{"learn":[4.744002932],"iteration":81,"passed_time":0.1837126033,"remaining_time":0.04032715682},
{"learn":[4.731700554],"iteration":82,"passed_time":0.1857117438,"remaining_time":0.03803734512},
{"learn":[4.723284153],"iteration":83,"passed_time":0.1879630874,"remaining_time":0.03580249283},
{"learn":[4.712232782],"iteration":84,"passed_time":0.1903315865,"remaining_time":0.03358792704},
{"learn":[4.703046867],"iteration":85,"passed_time":0.1918570445,"remaining_time":0.03123254213},
{"learn":[4.698601855],"iteration":86,"passed_time":0.1940795941,"remaining_time":0.02900039912},
{"learn":[4.692429407],"iteration":87,"passed_time":0.1955879529,"remaining_time":0.02667108448},
{"learn":[4.675027364],"iteration":88,"passed_time":0.1965492711,"remaining_time":0.02429260654},
{"learn":[4.662368584],"iteration":89,"passed_time":0.1976806328,"remaining_time":0.02196451475},
{"learn":[4.646206172],"iteration":90,"passed_time":0.1999515484,"remaining_time":0.01977542786},
{"learn":[4.641245848],"iteration":91,"passed_time":0.2023500852,"remaining_time":0.01759565958},
{"learn":[4.633900435],"iteration":92,"passed_time":0.2047251369,"remaining_time":0.0154094189},
{"learn":[4.624738236],"iteration":93,"passed_time":0.2068560783,"remaining_time":0.01320357946},
{"learn":[4.612798287],"iteration":94,"passed_time":0.2091541076,"remaining_time":0.01100811093},
{"learn":[4.605222001],"iteration":95,"passed_time":0.2110819291,"remaining_time":0.008795080379},
{"learn":[4.601725912],"iteration":96,"passed_time":0.2133892938,"remaining_time":0.00659966888},
{"learn":[4.59722371],"iteration":97,"passed_time":0.2158765521,"remaining_time":0.004405643921},
{"learn":[4.580235665],"iteration":98,"passed_time":0.2182145426,"remaining_time":0.002204187299},
{"learn":[4.57591791],"iteration":99,"passed_time":0.2204897945,"remaining_time":0}
]}